JiqiZhixin2020NianduJiaochengHejiErFix1/README.md
JiqiZhixin2020NianduJiaochengHejiErFix1/__init__.py
JiqiZhixin2020NianduJiaochengHejiErFix1/__main__.py
JiqiZhixin2020NianduJiaochengHejiErFix1/file.epub
JiqiZhixin2020NianduJiaochengHejiErFix1/index.html
JiqiZhixin2020NianduJiaochengHejiErFix1/css/__init__.py
JiqiZhixin2020NianduJiaochengHejiErFix1/css/annotations.css
JiqiZhixin2020NianduJiaochengHejiErFix1/css/main.css
JiqiZhixin2020NianduJiaochengHejiErFix1/css/normalize.css
JiqiZhixin2020NianduJiaochengHejiErFix1/css/popup.css
JiqiZhixin2020NianduJiaochengHejiErFix1/font/__init__.py
JiqiZhixin2020NianduJiaochengHejiErFix1/font/fontello.eot
JiqiZhixin2020NianduJiaochengHejiErFix1/font/fontello.svg
JiqiZhixin2020NianduJiaochengHejiErFix1/font/fontello.ttf
JiqiZhixin2020NianduJiaochengHejiErFix1/font/fontello.woff
JiqiZhixin2020NianduJiaochengHejiErFix1/img/__init__.py
JiqiZhixin2020NianduJiaochengHejiErFix1/img/annotator-glyph-sprite.png
JiqiZhixin2020NianduJiaochengHejiErFix1/img/annotator-icon-sprite.png
JiqiZhixin2020NianduJiaochengHejiErFix1/img/apple-touch-icon.png
JiqiZhixin2020NianduJiaochengHejiErFix1/img/cancelfullscreen.png
JiqiZhixin2020NianduJiaochengHejiErFix1/img/close.png
JiqiZhixin2020NianduJiaochengHejiErFix1/img/fullscreen.png
JiqiZhixin2020NianduJiaochengHejiErFix1/img/loader.gif
JiqiZhixin2020NianduJiaochengHejiErFix1/img/menu-icon.png
JiqiZhixin2020NianduJiaochengHejiErFix1/img/save.png
JiqiZhixin2020NianduJiaochengHejiErFix1/img/saved.png
JiqiZhixin2020NianduJiaochengHejiErFix1/img/settings-s.png
JiqiZhixin2020NianduJiaochengHejiErFix1/img/settings.png
JiqiZhixin2020NianduJiaochengHejiErFix1/img/star.png
JiqiZhixin2020NianduJiaochengHejiErFix1/js/__init__.py
JiqiZhixin2020NianduJiaochengHejiErFix1/js/epub.js
JiqiZhixin2020NianduJiaochengHejiErFix1/js/epub.min.js
JiqiZhixin2020NianduJiaochengHejiErFix1/js/epub.min.map
JiqiZhixin2020NianduJiaochengHejiErFix1/js/hooks.min.js
JiqiZhixin2020NianduJiaochengHejiErFix1/js/hooks.min.map
jiqi_zhixin_2020_niandu_jiaocheng_heji_er_fix1-2025.3.25.1.dist-info/METADATA
jiqi_zhixin_2020_niandu_jiaocheng_heji_er_fix1-2025.3.25.1.dist-info/WHEEL
jiqi_zhixin_2020_niandu_jiaocheng_heji_er_fix1-2025.3.25.1.dist-info/entry_points.txt
jiqi_zhixin_2020_niandu_jiaocheng_heji_er_fix1-2025.3.25.1.dist-info/top_level.txt
jiqi_zhixin_2020_niandu_jiaocheng_heji_er_fix1-2025.3.25.1.dist-info/RECORD
